super_bario/__init__.py
super_bario/progress.py
super_bario-0.3.7.dist-info/licenses/LICENSE
super_bario-0.3.7.dist-info/METADATA
super_bario-0.3.7.dist-info/WHEEL
super_bario-0.3.7.dist-info/top_level.txt
super_bario-0.3.7.dist-info/RECORD
