Metadata-Version: 2.4
Name: super-bario
Version: 0.3.7
Summary: Super Bario: a powerful Python library for multi-bar, multi-layout terminal progress indicators with themes, widgets, and thread-safe updates.
Author: Igor Iatsenko
License-Expression: MIT
Project-URL: Homepage, https://github.com/iserpent/super-bario
Project-URL: Source, https://github.com/iserpent/super-bario
Project-URL: Issues, https://github.com/iserpent/super-bario/issues
Keywords: progress,progressbar,progress-bar,progress-indicator,terminal,console,cli,tui,terminal-ui,spinner,layout,widgets,dashboard,multibar,thread-safe,super-bario
Classifier: Development Status :: 5 - Production/Stable
Classifier: Intended Audience :: Developers
Classifier: Environment :: Console
Classifier: Programming Language :: Python :: 3
Classifier: Programming Language :: Python :: 3.8
Classifier: Programming Language :: Python :: 3.9
Classifier: Programming Language :: Python :: 3.10
Classifier: Programming Language :: Python :: 3.11
Classifier: Programming Language :: Python :: 3.12
Classifier: Topic :: Software Development :: Libraries
Classifier: Topic :: Terminals
Requires-Python: >=3.8
License-File: LICENSE
Dynamic: license-file
